{
  "type": "GROUP",
"name": "All Requests",
"path": "",
"pathFormatted": "group_missing-name--1146707516",
"stats": {
    "name": "All Requests",
    "numberOfRequests": {
        "total": 4,
        "ok": 4,
        "ko": 0
    },
    "minResponseTime": {
        "total": 5,
        "ok": 5,
        "ko": 0
    },
    "maxResponseTime": {
        "total": 21,
        "ok": 21,
        "ko": 0
    },
    "meanResponseTime": {
        "total": 9,
        "ok": 9,
        "ko": 0
    },
    "standardDeviation": {
        "total": 7,
        "ok": 7,
        "ko": 0
    },
    "percentiles1": {
        "total": 5,
        "ok": 5,
        "ko": 0
    },
    "percentiles2": {
        "total": 21,
        "ok": 21,
        "ko": 0
    },
    "percentiles3": {
        "total": 21,
        "ok": 21,
        "ko": 0
    },
    "percentiles4": {
        "total": 21,
        "ok": 21,
        "ko": 0
    },
    "group1": {
    "name": "t < 800 ms",
    "htmlName": "t < 800 ms",
    "count": 4,
    "percentage": 100.0
},
    "group2": {
    "name": "800 ms <= t < 1200 ms",
    "htmlName": "t >= 800 ms <br> t < 1200 ms",
    "count": 0,
    "percentage": 0.0
},
    "group3": {
    "name": "t >= 1200 ms",
    "htmlName": "t >= 1200 ms",
    "count": 0,
    "percentage": 0.0
},
    "group4": {
    "name": "failed",
    "htmlName": "failed",
    "count": 0,
    "percentage": 0.0
},
    "meanNumberOfRequestsPerSecond": {
        "total": 0.2222222222222222,
        "ok": 0.2222222222222222,
        "ko": 0
    }
},
"contents": {
"req_create-car-task-2113443093": {
        "type": "REQUEST",
        "name": "Create Car Task",
"path": "Create Car Task",
"pathFormatted": "req_create-car-task-2113443093",
"stats": {
    "name": "Create Car Task",
    "numberOfRequests": {
        "total": 1,
        "ok": 1,
        "ko": 0
    },
    "minResponseTime": {
        "total": 21,
        "ok": 21,
        "ko": 0
    },
    "maxResponseTime": {
        "total": 21,
        "ok": 21,
        "ko": 0
    },
    "meanResponseTime": {
        "total": 21,
        "ok": 21,
        "ko": 0
    },
    "standardDeviation": {
        "total": 0,
        "ok": 0,
        "ko": 0
    },
    "percentiles1": {
        "total": 21,
        "ok": 21,
        "ko": 0
    },
    "percentiles2": {
        "total": 21,
        "ok": 21,
        "ko": 0
    },
    "percentiles3": {
        "total": 21,
        "ok": 21,
        "ko": 0
    },
    "percentiles4": {
        "total": 21,
        "ok": 21,
        "ko": 0
    },
    "group1": {
    "name": "t < 800 ms",
    "htmlName": "t < 800 ms",
    "count": 1,
    "percentage": 100.0
},
    "group2": {
    "name": "800 ms <= t < 1200 ms",
    "htmlName": "t >= 800 ms <br> t < 1200 ms",
    "count": 0,
    "percentage": 0.0
},
    "group3": {
    "name": "t >= 1200 ms",
    "htmlName": "t >= 1200 ms",
    "count": 0,
    "percentage": 0.0
},
    "group4": {
    "name": "failed",
    "htmlName": "failed",
    "count": 0,
    "percentage": 0.0
},
    "meanNumberOfRequestsPerSecond": {
        "total": 0.05555555555555555,
        "ok": 0.05555555555555555,
        "ko": 0
    }
}
    },"req_check-task-stat--726021195": {
        "type": "REQUEST",
        "name": "Check Task Status",
"path": "Check Task Status",
"pathFormatted": "req_check-task-stat--726021195",
"stats": {
    "name": "Check Task Status",
    "numberOfRequests": {
        "total": 3,
        "ok": 3,
        "ko": 0
    },
    "minResponseTime": {
        "total": 5,
        "ok": 5,
        "ko": 0
    },
    "maxResponseTime": {
        "total": 5,
        "ok": 5,
        "ko": 0
    },
    "meanResponseTime": {
        "total": 5,
        "ok": 5,
        "ko": 0
    },
    "standardDeviation": {
        "total": 0,
        "ok": 0,
        "ko": 0
    },
    "percentiles1": {
        "total": 5,
        "ok": 5,
        "ko": 0
    },
    "percentiles2": {
        "total": 5,
        "ok": 5,
        "ko": 0
    },
    "percentiles3": {
        "total": 5,
        "ok": 5,
        "ko": 0
    },
    "percentiles4": {
        "total": 5,
        "ok": 5,
        "ko": 0
    },
    "group1": {
    "name": "t < 800 ms",
    "htmlName": "t < 800 ms",
    "count": 3,
    "percentage": 100.0
},
    "group2": {
    "name": "800 ms <= t < 1200 ms",
    "htmlName": "t >= 800 ms <br> t < 1200 ms",
    "count": 0,
    "percentage": 0.0
},
    "group3": {
    "name": "t >= 1200 ms",
    "htmlName": "t >= 1200 ms",
    "count": 0,
    "percentage": 0.0
},
    "group4": {
    "name": "failed",
    "htmlName": "failed",
    "count": 0,
    "percentage": 0.0
},
    "meanNumberOfRequestsPerSecond": {
        "total": 0.16666666666666666,
        "ok": 0.16666666666666666,
        "ko": 0
    }
}
    }
}

}